[{"id":"22355","title":"A Book","imageUrl":"https://www.publicdomainpictures.net/pictures/10000/velka/1-1210009435EGmE.jpg","description":"This is an awesome book!","price":"19"},{"title":"sdf","imageUrl":"sdfsdf","description":"asdasdf","price":"12","id":"0.6761673412308586"},{"title":"aefE","imageUrl":"https://www.google.com/url?sa=i&url=https%3A%2F%2Fwww.scientificamerican.com%2Farticle%2Fhow-house-cats-evolved%2F&psig=AOvVaw193TCduPA_rJVxIP8U2pf4&ust=1735022564911000&source=images&cd=vfe&opi=89978449&ved=0CBAQjRxqFwoTCJDq6u-kvYoDFQAAAAAdAAAAABAE","description":"SFASF","price":"1","id":"0.923464403894015"}]